{"name": "Ponti | Luxury Furniture by Christopher Guy Singapore", "price": "18882", "currency": "S$", "width": "205", "height": "60", "depth": "115", "dimension_unit": "cm", "description": "Named after the Italian master of Modernism, designer, architect, artist and publisher Gio Ponti, this 2-seater sofa forms part of a collection of sofas and sectional sofas. Featuring straight lines and hand-carved diamond detailing on the legs, the contemporary look is softened by the supreme comfort of CG upholstery.", "image_url": "https://scene7.christopherguy.com/ir/render/ChristopherGuyRender/60-0690?wid=800&obj=fabric/area_1&src=FF-090&illum=0&obj=fabric/pillows/area_1&src=FF-090&illum=0", "product_code": "60-0690", "extension": "jpeg"}