{"name": "Jaime | Luxury Furniture by Christopher Guy Singapore", "price": "3353", "currency": "S$", "width": "45", "height": "45", "depth": "45", "dimension_unit": "cm", "description": "With a cone-shaped base and upholstered seat, this stool is a beautifully elegant accent piece for any style of room. Perfect for accessorizing a bathroom or dressing room, or as a dressing table seat.", "image_url": "https://scene7.christopherguy.com/ir/render/ChristopherGuyRender/60-0770-finish-v3?wid=800&obj=finish&src=60-0770_bronzage-v3&res=40&obj=fabric/area_1&src=DD-064&illum=0", "product_code": "60-0770", "extension": "jpeg"}