{"name": "Dune Lamp", "price": "None", "currency": "None", "width": "26.5", "height": "33", "depth": "12", "dimension_unit": "cm", "description": "The Dune lamp, whose massive structure is made in « Purpura ébène» satin walnut, becomes the masterful element of any interior. Its smooth shape recalls pebbles shaped by time. Matter: « Purpura ébène» satin walnut, black patina brass, aquarelle paper shade", "image_url": "https://www.studioliaigre.com/content/uploads/2017/06/dune-2.jpg", "product_code": "None", "extension": "jpeg"}