{"name": "Charbon Bedside Table", "price": "None", "currency": "None", "width": "65", "height": "48", "depth": "50", "dimension_unit": "cm", "description": "The Charbon Bedside Table has an Asian influence, reflected in its geometric shape, sleek lines, and clever craftsmanship. The table fits on either end of a bed and is offered in a variety of oak or pine frames, finished with a lacquer top, suitable for any interior.", "image_url": "https://www.studioliaigre.com/content/uploads/2018/04/Charbon-1.jpg", "product_code": "None", "extension": "jpeg"}