{"name": "DUO | Floor mirror", "price": "None", "currency": "None", "width": "None", "height": "200", "depth": "None", "dimension_unit": "cm", "description": "The Duo floor mirror is the full-length mirror with an elegant frame made of solid ash wood with a handcrafted gouge finish, giving it a striking three-dimensional appearance. With a height of 200 cm, it is ideal for the bedroom and entryway.", "image_url": "https://www.ceccotticollezioni.it/wp-content/uploads/2023/04/DUO-Floor-Mirror-1.jpg", "product_code": "None", "extension": "jpeg"}