{"name": "Brad | Comodino - Ceccotti Collezioni", "price": "None", "currency": "None", "width": "None", "height": "None", "depth": "None", "dimension_unit": "cm", "description": "Brad comodino, nato dallo Studio CC nel 2010, parla il linguaggio della contemporaneità senza lasciarsi andare ad eccessi. Il volume, quasi monolitico, è alleggerito dalla linea morbida delle gambe e dai due cassetti. Realizzato in massello di noce americano e multistrato impiallacciato, è declinabile in quattro finiture di pregio che sottolineano la qualità che Ceccotti Collezioni porta nel Made in Italy. Le due diverse misure in larghezza lo rendono adatto a diverse esigenze. Per completare l'arredo della zona notte può essere affiancata al letto Brad e alla cassettiera Brad, facenti parte della stessa famiglia.", "image_url": "https://www.ceccotticollezioni.it/wp-content/uploads/2020/06/50462brad_comodino_01.jpg", "product_code": "None", "extension": "jpeg"}