{"name": "Ely Rug - Granite/Lead White", "price": "3295", "currency": "£", "width": "274", "height": "None", "depth": "366", "dimension_unit": "cm", "description": "Eight is the magic number as far as the Ely is concerned. Decorated with octagons and abstract emblems in muted shades, it's just the rug for a sitting room or guest bedroom. Your friends and family will be floored by its intricate detailing and clever ability to complement furniture both modern and traditional.", "image_url": "https://www.oka.com/media/catalog/product/e/l/ely-rug-granite-lead-white-a16318-1-22-1340-140-01.png?width=585&height=658&canvas=585,658&quality=80&fit=bounds", "product_code": "A16318-1-22-1340-140", "extension": "png", "styles": [{"style_name": ".CONTEMPORARY", "weight": 2}, {"style_name": ".MINIMALISM", "weight": 0}, {"style_name": ".MID_CENTURY_MODERN", "weight": 2}, {"style_name": ".COUNTRY", "weight": 2}, {"style_name": ".COSTAL", "weight": 6}, {"style_name": ".RUSTIC", "weight": 11}, {"style_name": ".ART_DECO", "weight": 1}, {"style_name": ".INDUSTRIAL", "weight": 1}, {"style_name": ".SHABBY_CHIC", "weight": 2}, {"style_name": ".CLASSICAL_SLASH_TRADITIONAL", "weight": 4}, {"style_name": ".BOHEMIAN", "weight": 47}, {"style_name": ".ELECTRIC_SLASH_RETRO", "weight": 0}, {"style_name": ".TRANSITIONAL", "weight": 5}, {"style_name": ".CHALET", "weight": 5}, {"style_name": ".FRENCH_CLASSICAL", "weight": 1}, {"style_name": ".SCANDINAVIAN", "weight": 4}]}